python_notion_exporter/__init__.py
python_notion_exporter/main.py
python_notion_exporter-1.0.6.dist-info/LICENSE
python_notion_exporter-1.0.6.dist-info/METADATA
python_notion_exporter-1.0.6.dist-info/WHEEL
python_notion_exporter-1.0.6.dist-info/top_level.txt
python_notion_exporter-1.0.6.dist-info/RECORD
