Metadata-Version: 2.1
Name: python-notion-exporter
Version: 1.0.6
Summary: Export and download Notion pages asynchronously
Home-page: https://github.com/tomchen/example_pypi_package
Author: Roméo Phillips
Author-email: phillipsromeo@gmail.com
Project-URL: Documentation, https://github.com/Strvm/python-notion-exporter
Project-URL: Bug Reports, https://github.com/Strvm/python-notion-exporter
Project-URL: Source Code, https://github.com/Strvm/python-notion-exporter
Keywords: notion,notion-api,python_notion_exporter,notion-downloader,notion-py
Classifier: Development Status :: 5 - Production/Stable
Classifier: Intended Audience :: Developers
Classifier: Topic :: Software Development :: Build Tools
Classifier: Programming Language :: Python :: 3
Classifier: Programming Language :: Python :: 3.6
Classifier: Programming Language :: Python :: 3.7
Classifier: Programming Language :: Python :: 3.8
Classifier: Programming Language :: Python :: 3.9
Classifier: Programming Language :: Python :: 3 :: Only
Classifier: License :: OSI Approved :: MIT License
Classifier: Operating System :: OS Independent
Requires-Python: >=3.6
License-File: LICENSE
Requires-Dist: requests
Requires-Dist: tqdm
Provides-Extra: dev
Requires-Dist: check-manifest ; extra == 'dev'
